MANIFEST.in
README.md
setup.py
SliQSim/.git
SliQSim/.gitignore
SliQSim/Makefile
SliQSim/README.md
SliQSim/cudd/.gitignore
SliQSim/cudd/Doxyfile.in
SliQSim/cudd/LICENSE
SliQSim/cudd/Makefile
SliQSim/cudd/Makefile.am
SliQSim/cudd/Makefile.in
SliQSim/cudd/README
SliQSim/cudd/RELEASE.NOTES
SliQSim/cudd/aclocal.m4
SliQSim/cudd/config.h
SliQSim/cudd/config.h.in
SliQSim/cudd/config.status
SliQSim/cudd/configure
SliQSim/cudd/configure.ac
SliQSim/cudd/groups.dox
SliQSim/cudd/libtool
SliQSim/cudd/stamp-h1
SliQSim/cudd/build-aux/ar-lib
SliQSim/cudd/build-aux/compile
SliQSim/cudd/build-aux/config.guess
SliQSim/cudd/build-aux/config.sub
SliQSim/cudd/build-aux/depcomp
SliQSim/cudd/build-aux/install-sh
SliQSim/cudd/build-aux/ltmain.sh
SliQSim/cudd/build-aux/missing
SliQSim/cudd/build-aux/tap-driver.sh
SliQSim/cudd/cplusplus/.dirstamp
SliQSim/cudd/cplusplus/Included.am
SliQSim/cudd/cplusplus/cuddObj.cc
SliQSim/cudd/cplusplus/cuddObj.hh
SliQSim/cudd/cplusplus/multi.out
SliQSim/cudd/cplusplus/test.out
SliQSim/cudd/cplusplus/test_obj.test.in
SliQSim/cudd/cplusplus/testmulti.cc
SliQSim/cudd/cplusplus/testobj.cc
SliQSim/cudd/cplusplus/.deps/.dirstamp
SliQSim/cudd/cplusplus/.deps/cplusplus_libobj_la-cuddObj.Plo
SliQSim/cudd/cplusplus/.deps/cplusplus_testmulti-testmulti.Po
SliQSim/cudd/cplusplus/.deps/cplusplus_testobj-testobj.Po
SliQSim/cudd/cplusplus/.deps/cudd_libcudd_la-cuddObj.Plo
SliQSim/cudd/cudd/.dirstamp
SliQSim/cudd/cudd/Included.am
SliQSim/cudd/cudd/cudd.h
SliQSim/cudd/cudd/cuddAPI.c
SliQSim/cudd/cudd/cuddAddAbs.c
SliQSim/cudd/cudd/cuddAddApply.c
SliQSim/cudd/cudd/cuddAddFind.c
SliQSim/cudd/cudd/cuddAddInv.c
SliQSim/cudd/cudd/cuddAddIte.c
SliQSim/cudd/cudd/cuddAddNeg.c
SliQSim/cudd/cudd/cuddAddWalsh.c
SliQSim/cudd/cudd/cuddAndAbs.c
SliQSim/cudd/cudd/cuddAnneal.c
SliQSim/cudd/cudd/cuddApa.c
SliQSim/cudd/cudd/cuddApprox.c
SliQSim/cudd/cudd/cuddBddAbs.c
SliQSim/cudd/cudd/cuddBddCorr.c
SliQSim/cudd/cudd/cuddBddIte.c
SliQSim/cudd/cudd/cuddBridge.c
SliQSim/cudd/cudd/cuddCache.c
qiskit_sliqsim_provider.egg-info/PKG-INFO
qiskit_sliqsim_provider.egg-info/SOURCES.txt
qiskit_sliqsim_provider.egg-info/dependency_links.txt
qiskit_sliqsim_provider.egg-info/top_level.txt