Metadata-Version: 2.1
Name: qiskit-sliqsim-provider
Version: 0.0.6
Summary: SliQSim simulator
Home-page: https://github.com/NTU-ALComLab/SliQSim-Qiskit-Interface
Author: Yuan-Hung Tsai, Jie-Hong R. Jiang, Chiao-Shan Jhang, Justin Chen
Author-email: matthewyhtsai@gmail.com
License: UNKNOWN
Platform: UNKNOWN
Classifier: Programming Language :: Python :: 3
Classifier: License :: OSI Approved :: MIT License
Classifier: Operating System :: OS Independent
Requires-Python: >=3.8
